gio/__init__.py
gio/_version.py
gio/closure.py
gio/esri.py
gio/iesx.py
gio/logo.py
gio/opendtect.py
gio/random.py
gio/surfer.py
gio/unmap.py
gio/xarray.py
gio/xy_to_grid.py
gio/zmap.py
gio-0.2.0.dist-info/AUTHORS.md
gio-0.2.0.dist-info/LICENSE
gio-0.2.0.dist-info/METADATA
gio-0.2.0.dist-info/WHEEL
gio-0.2.0.dist-info/top_level.txt
gio-0.2.0.dist-info/RECORD
