Metadata-Version: 2.1
Name: gio
Version: 0.2.0
Summary: Create xarray.DataArrays from various subsurface data formats.
Author-email: Agile Scientific <hello@agilescientific.com>
License: Apache License
Project-URL: documentation, https://code.agilescientific.com/gio/
Project-URL: repository, https://github.com/agilescientific/gio
Keywords: data loading,data management,geoscience,geospatial
Classifier: Intended Audience :: Science/Research
Classifier: Topic :: Scientific/Engineering :: Information Analysis
Classifier: Development Status :: 4 - Beta
Classifier: Natural Language :: English
Classifier: Programming Language :: Python :: 3.8
Classifier: Programming Language :: Python :: 3.9
Classifier: Programming Language :: Python :: 3.10
Classifier: Programming Language :: Python :: 3.11
Classifier: License :: OSI Approved :: Apache Software License
Classifier: Operating System :: OS Independent
Requires-Python: >=3.8
License-File: LICENSE
License-File: AUTHORS.md
Requires-Dist: scipy
Requires-Dist: xarray
Requires-Dist: matplotlib
Requires-Dist: shapely
Requires-Dist: zmapio
Requires-Dist: unmap
Provides-Extra: dev
Requires-Dist: build ; extra == 'dev'
Requires-Dist: pytest ; extra == 'dev'
Requires-Dist: coverage[toml] ; extra == 'dev'
Requires-Dist: pytest-cov ; extra == 'dev'
Requires-Dist: sphinx ; extra == 'dev'
Requires-Dist: sphinxcontrib-apidoc ; extra == 'dev'
Requires-Dist: sphinx-copybutton ; extra == 'dev'
Requires-Dist: furo ; extra == 'dev'
Requires-Dist: myst-nb ; extra == 'dev'
Requires-Dist: jupyter ; extra == 'dev'
Requires-Dist: requests ; extra == 'dev'
Requires-Dist: geopandas ; extra == 'dev'
Provides-Extra: geopandas
Requires-Dist: geopandas ; extra == 'geopandas'
